topsis/__init__.py
topsis/__main__.py
Topsis_Ria_102203069-1.0.0.dist-info/LICENSE
Topsis_Ria_102203069-1.0.0.dist-info/METADATA
Topsis_Ria_102203069-1.0.0.dist-info/WHEEL
Topsis_Ria_102203069-1.0.0.dist-info/entry_points.txt
Topsis_Ria_102203069-1.0.0.dist-info/top_level.txt
Topsis_Ria_102203069-1.0.0.dist-info/RECORD
